docp_loaders/__init__.py
docp_loaders/_version.py
docp_loaders/libs/__init__.py
docp_loaders/libs/changelog.py
docp_loaders/libs/utilities.py
docp_loaders/loaders/__init__.py
docp_loaders/loaders/chromapdfloader.py
docp_loaders/loaders/chromapptxloader.py
docp_loaders/objects/__init__.py
docp_loaders/objects/_chromabaseloader.py
docp_loaders/objects/_chromabasepdfloader.py
docp_loaders/objects/_chromabasepptxloader.py
docp_loaders-1.0.0.dist-info/licenses/LICENSE
docp_loaders-1.0.0.dist-info/METADATA
docp_loaders-1.0.0.dist-info/WHEEL
docp_loaders-1.0.0.dist-info/top_level.txt
docp_loaders-1.0.0.dist-info/RECORD
