Metadata-Version: 2.4
Name: docp-loaders
Version: 1.0.0
Summary: A basic document parsing utility. (Loaders)
Author-email: The Developers <development@s3dev.uk>
License-Expression: GPL-3.0-or-later
Project-URL: Documentation, https://docp-loaders.readthedocs.io
Project-URL: Homepage, https://github.com/s3dev/docp-loaders
Project-URL: Repository, https://github.com/s3dev/docp-loaders
Keywords: document,library,loading,utility,utilities
Classifier: Development Status :: 5 - Production/Stable
Classifier: Intended Audience :: Developers
Classifier: Intended Audience :: End Users/Desktop
Classifier: Programming Language :: Python :: 3.11
Classifier: Programming Language :: Python :: 3.12
Classifier: Programming Language :: Python :: 3.13
Classifier: Programming Language :: Python :: 3.14
Classifier: Programming Language :: Python :: Implementation :: CPython
Classifier: Operating System :: POSIX :: Linux
Classifier: Operating System :: Microsoft :: Windows
Classifier: Topic :: Software Development
Classifier: Topic :: Software Development :: Libraries
Classifier: Topic :: Utilities
Requires-Python: >=3.11
License-File: LICENSE
Requires-Dist: chromadb>=1.3.7
Requires-Dist: docp_core>=1.0.1
Requires-Dist: docp_dbi>=1.0.0
Requires-Dist: docp_docling>=1.0.0
Requires-Dist: docp_parsers>=1.0.0
Requires-Dist: langchain_text_splitters>=1.1.0
Requires-Dist: utils4>=1.8.1
Dynamic: license-file
